alaas/__init__.py
alaas/version.py
alaas/client/__init__.py
alaas/client/client.py
alaas/client/utils.py
alaas/metric/__init__.py
alaas/server/__init__.py
alaas/server/server.py
alaas/server/executors/__init__.py
alaas/server/executors/al_torch.py
alaas/server/executors/cl_torch.py
alaas/server/preprocessor/__init__.py
alaas/server/preprocessor/image.py
alaas/server/preprocessor/text.py
alaas/server/strategy/__init__.py
alaas/server/strategy/base.py
alaas/server/strategy/cluster.py
alaas/server/strategy/diversity.py
alaas/server/strategy/random.py
alaas/server/strategy/uncertainty.py
alaas/server/util/__init__.py
alaas/server/util/cfg_manager.py
alaas/server/util/data_util.py
alaas/types/__init__.py
alaas/types/models/__init__.py
alaas/types/models/al_model.py
alaas/types/models/al_strategy.py
alaas/types/models/config.py
alaas/types/models/utils.py
examples/__init__.py
examples/image/__init__.py
examples/image/image_clf_client.py
examples/image/image_clf_server.py
examples/text/__init__.py
examples/text/text_clf_client.py
examples/text/text_clf_server.py
tests/__init__.py
alaas-0.2.1.dist-info/LICENSE
alaas-0.2.1.dist-info/METADATA
alaas-0.2.1.dist-info/WHEEL
alaas-0.2.1.dist-info/top_level.txt
alaas-0.2.1.dist-info/RECORD
