Metadata-Version: 2.1
Name: alaas
Version: 0.2.1
Summary: A Distributed MLOps System for Efficient Active Learning
Home-page: https://github.com/MLSysOps/alaas
Download-URL: https://github.com/MLSysOps/alaas/archive/master.zip
Author: Yizheng Huang
Author-email: huangyz0918@gmail.com
Keywords: active learning,deep learning,MLOps,data mining,neural networks
Classifier: Development Status :: 5 - Production/Stable
Classifier: Intended Audience :: Education
Classifier: Intended Audience :: Financial and Insurance Industry
Classifier: Intended Audience :: Science/Research
Classifier: Intended Audience :: Developers
Classifier: Intended Audience :: Information Technology
Classifier: License :: OSI Approved :: Apache Software License
Classifier: Programming Language :: Python :: 3
Classifier: Operating System :: OS Independent
License-File: LICENSE
Requires-Dist: numpy
Requires-Dist: boto3
Requires-Dist: scikit-learn
Requires-Dist: setuptools
Requires-Dist: tqdm
Requires-Dist: pydantic
Requires-Dist: pyyaml
Requires-Dist: requests
Requires-Dist: opencv-python
Requires-Dist: pillow
Requires-Dist: jina
Requires-Dist: transformers
Requires-Dist: sentencepiece
